pbm_liumou_Stable/IP.py
pbm_liumou_Stable/__init__.py
pbm_liumou_stable-1.0.0.dist-info/METADATA
pbm_liumou_stable-1.0.0.dist-info/WHEEL
pbm_liumou_stable-1.0.0.dist-info/licenses/LICENSE
pbm_liumou_stable-1.0.0.dist-info/RECORD
