Metadata-Version: 2.1
Name: pbm_liumou_Stable
Version: 1.0.0
Summary: 这是一个Python日常开发中常用的数据、功能基础处理函数，例如IP地址切割，子网掩码换算等
Project-URL: Homepage, https://gitee.com/liumou_site/pbm
Project-URL: Bug Tracker, https://gitee.com/liumou_site/pbm/issues
Author-email: 坐公交也用券 <liumou.site@qq.com>
License-File: LICENSE
Classifier: License :: OSI Approved :: MIT License
Classifier: Operating System :: OS Independent
Classifier: Programming Language :: Python :: 3
Requires-Python: >=3.0
